{
    "parent": "item/generated",
    "textures": {
        "layer0": "hats/crossbow_standby"
    },
    "display": {
        "thirdperson_righthand": {
            "rotation": [ -90, 0, -60 ],
            "translation": [ 2, 0.1, -3 ],
            "scale": [ 0.9, 0.9, 0.9 ]
        },
        "thirdperson_lefthand": {
            "rotation": [ -90, 0, 30 ],
            "translation": [ 2, 0.1, -3 ],
            "scale": [ 0.9, 0.9, 0.9 ]
        },
        "firstperson_righthand": {
            "rotation": [ -90, 0, -55 ],
            "translation": [ 1.13, 3.2, 1.13],
            "scale": [ 0.68, 0.68, 0.68 ]
        },
        "firstperson_lefthand": {
            "rotation": [ -90, 0, 35 ],
            "translation": [ 1.13, 3.2, 1.13],
            "scale": [ 0.68, 0.68, 0.68 ]
        }
    },
    "overrides": [
        {
            "predicate": {
                "pulling": 1
            },
            "model": "hats/crossbow_pulling_0_s"
        },
        {
            "predicate": {
                "pulling": 1,
                "pull": 0.58
            },
            "model": "hats/crossbow_pulling_1_s"
        },
        {
            "predicate": {
                "pulling": 1,
                "pull": 1.0
            },
            "model": "hats/crossbow_pulling_2_s"
        },
        {
            "predicate": {
                "charged": 1
            },
            "model": "hats/crossbow_arrow_s"
        },
        {
            "predicate": {
                "charged": 1,
                "firework": 1
            },
            "model": "hats/crossbow_firework"
        }
    ]
}
